odoo/addons/partner_contact_tags_in_popup/README.rst
odoo/addons/partner_contact_tags_in_popup/__init__.py
odoo/addons/partner_contact_tags_in_popup/__manifest__.py
odoo/addons/partner_contact_tags_in_popup/i18n/it.po
odoo/addons/partner_contact_tags_in_popup/i18n/partner_contact_tags_in_popup.pot
odoo/addons/partner_contact_tags_in_popup/readme/CONTRIBUTORS.md
odoo/addons/partner_contact_tags_in_popup/readme/DESCRIPTION.md
odoo/addons/partner_contact_tags_in_popup/static/description/icon.png
odoo/addons/partner_contact_tags_in_popup/static/description/index.html
odoo/addons/partner_contact_tags_in_popup/views/res_partner_views.xml
odoo_addon_partner_contact_tags_in_popup-18.0.1.0.0.2.dist-info/METADATA
odoo_addon_partner_contact_tags_in_popup-18.0.1.0.0.2.dist-info/WHEEL
odoo_addon_partner_contact_tags_in_popup-18.0.1.0.0.2.dist-info/top_level.txt
odoo_addon_partner_contact_tags_in_popup-18.0.1.0.0.2.dist-info/RECORD
