Metadata-Version: 2.1
Name: odoo-addon-partner_contact_tags_in_popup
Version: 18.0.1.0.0.2
Requires-Python: >=3.10
Requires-Dist: odoo==18.0.*
Summary: Display a contact's tags in the 'Contacts & Addresses' pop-up form view.
Home-page: https://github.com/OCA/partner-contact
License: AGPL-3
Author: Coop IT Easy SC, Odoo Community Association (OCA)
Author-email: support@odoo-community.org
Classifier: Programming Language :: Python
Classifier: Framework :: Odoo
Classifier: Framework :: Odoo :: 18.0
Classifier: License :: OSI Approved :: GNU Affero General Public License v3
